ndf_parse/__init__.py
ndf_parse/converter.py
ndf_parse/parser.py
ndf_parse/printer.py
ndf_parse/traverser.py
ndf_parse/bin/ndf.dll
ndf_parse/model/__init__.py
ndf_parse/model/__init__.pyi
ndf_parse/model/abc.py
ndf_parse-0.2.0.dist-info/LICENSE
ndf_parse-0.2.0.dist-info/METADATA
ndf_parse-0.2.0.dist-info/WHEEL
ndf_parse-0.2.0.dist-info/top_level.txt
ndf_parse-0.2.0.dist-info/RECORD
