Metadata-Version: 2.1
Name: ndf-parse
Version: 0.2.0
Summary: A package for parsing and editing Eugen Systems ndf files.
Author: Ulibos
License: The MIT License (MIT)
Project-URL: Homepage, https://github.com/Ulibos/ndf-parse
Project-URL: Documentation, https://ulibos.github.io/ndf-parse
Keywords: ndf,parser,parsing
Classifier: Development Status :: 5 - Production/Stable
Classifier: Environment :: Console
Classifier: Intended Audience :: Developers
Classifier: Intended Audience :: Other Audience
Classifier: License :: OSI Approved :: MIT License
Classifier: Programming Language :: Python :: 3
Classifier: Programming Language :: Python :: 3.8
Classifier: Programming Language :: Python :: 3.9
Classifier: Programming Language :: Python :: 3.10
Classifier: Programming Language :: Python :: 3.11
Classifier: Programming Language :: Python :: 3.12
Classifier: Topic :: File Formats
Requires-Python: >=3.8
License-File: LICENSE
Requires-Dist: tree-sitter~=0.21.0
Requires-Dist: typing-extensions; python_version < "3.11"
Provides-Extra: dev
Requires-Dist: sphinx~=7.0; extra == "dev"
Requires-Dist: furo~=2024.0; extra == "dev"
Requires-Dist: sphinx-multiversion~=0.2.4; extra == "dev"
